[
  {
    "titulo":"A Primeira Guerra Mundial e o declínio da Europa",
    "subtitulo":"Revoluções e Guerras",
    "check":false
  },
  {
    "titulo":"Da Revolução Russa ao stalinismo",
    "subtitulo":"Revoluções e Guerras",
    "check":false
  },
  {
    "titulo":"O entre guerras e a ascensão dosEstados Unidos da América",
    "subtitulo":"Revoluções e Guerras",
    "check":false
  },
  {
    "titulo":"Democracia em xeque: nazismoe fascismo",
    "subtitulo":"Revoluções e Guerras",
    "check":false
  },
  {
    "titulo":"A Segunda Guerra Mundial: o nazismo domina a Europa",
    "subtitulo":"Revoluções e Guerras",
    "check":false
  },
  {
    "titulo":"A Era Vargas–do governo provisório ao Estado Novo",
    "subtitulo":"O Mundo Pós-Guerra: Descolonização e Guerra Fria I",
    "check":false
  },
  {
    "titulo":"A política da Era Vargas para o Extremo Norte–a marcha para o Oeste e a “ocupação dos espaços vazios”",
    "subtitulo":"O Mundo Pós-Guerra: Descolonização e Guerra Fria I",
    "check":false
  },
  {
    "titulo":"Os Acordos de Washington e a“redenção  da  Amazônia”",
    "subtitulo":"O Mundo Pós-Guerra: Descolonização e Guerra Fria I",
    "check":false
  },
  {
    "titulo":"Superintendência de Valorização Econômica da Amazônia–Spvea",
    "subtitulo":"O Mundo Pós-Guerra: Descolonização e Guerra Fria I",
    "check":false
  },
  {
    "titulo":"O Estado e a classe trabalhadora no Brasil",
    "subtitulo":"O Mundo Pós-Guerra: Descolonização e Guerra Fria I",
    "check":false
  },
  {
    "titulo":"A nova ordem mundial e a Guerra Fria",
    "subtitulo":"O Mundo Pós-Guerra: Descolonização e Guerra Fria I",
    "check":false
  },
  {
    "titulo":"A revolução e o socialismo na China",
    "subtitulo":"O Mundo Pós-Guerra: Descolonização e Guerra Fria I",
    "check":false
  },
  {
    "titulo":"A Revolução Cubana e a Doutrina de Segurança Nacional",
    "subtitulo":"O Mundo Pós-Guerra: Descolonização e Guerra Fria I",
    "check":false
  },
  {
    "titulo":"A corrida espacial e a cultura no pós-guerra",
    "subtitulo":"O Mundo Pós-Guerra: Descolonização e Guerra Fria I",
    "check":false
  },
  {
    "titulo":"O Terceiro Mundo:A descolonizaçãoda Ásia e da África",
    "subtitulo":"O Mundo Pós-Guerra: Descolonização e Guerra Fria I",
    "check":false
  },
  {
    "titulo":"O Oriente Médio e seus impasses:o Estado de Israel e o conflito árabe-israelense",
    "subtitulo":"O Mundo Pós-Guerra: Descolonização e Guerra Fria I",
    "check":false
  },
  {
    "titulo":"Em nome do Corão:A Revolução Iraniana",
    "subtitulo":"O Mundo Pós-Guerra: Descolonização e Guerra Fria I",
    "check":false
  },
  {
    "titulo":"A América Latina no contexto do pós-guerra",
    "subtitulo":"O Mundo do Pós-guerra: Descolonização e Guerra Fria II",
    "check":false
  },
  {
    "titulo":"Nacionalismo e desenvolvimentismo",
    "subtitulo":"O Mundo do Pós-guerra: Descolonização e Guerra Fria II",
    "check":false
  },
  {
    "titulo":"O Brasil e a República democrática",
    "subtitulo":"O Mundo do Pós-guerra: Descolonização e Guerra Fria II",
    "check":false
  },
  {
    "titulo":"Brasil: a República dos generais",
    "subtitulo":"O Mundo do Pós-guerra: Descolonização e Guerra Fria II",
    "check":false
  },
  {
    "titulo":"O Regime militar e os grandes projetos para o Extremo Norte:Desenvolvimentismo,Integração nacional,Conflitos pela terra,A Zona Franca de Manaus",
    "subtitulo":"O Mundo do Pós-guerra: Descolonização e Guerra Fria II",
    "check":false
  },
  {
    "titulo":"Tempos de crise e a revolução técnico-científica",
    "subtitulo":"Novo milênio,novos desafios",
    "check":false
  },
  {
    "titulo":"A contracultura",
    "subtitulo":"Novo milênio,novos desafios",
    "check":false
  },
  {
    "titulo":"A conquista dos direitos civis",
    "subtitulo":"Novo milênio,novos desafios",
    "check":false
  },
  {
    "titulo":"Brasil:reencontro com ademocracia",
    "subtitulo":"Novo milênio,novos desafios",
    "check":false
  },
  {
    "titulo":"A era neoliberal",
    "subtitulo":"Novo milênio,novos desafios",
    "check":false
  },
  {
    "titulo":"A globalização e a nova ordem mundial",
    "subtitulo":"Novo milênio,novos desafios",
    "check":false
  }
]
